{
  "prepare_queue": {
    "installed": [],
    "uninstalled": []
  },
  "config_munge": {
    "files": {}
  },
  "installed_plugins": {
    "cordova-plugin-camera": {
      "PACKAGE_NAME": "com.aspire.aspireias"
    },
    "cordova-plugin-device": {
      "PACKAGE_NAME": "com.aspire.aspireias"
    },
    "cordova-plugin-file": {
      "PACKAGE_NAME": "com.aspire.aspireias"
    },
    "cordova-plugin-file-transfer": {
      "PACKAGE_NAME": "com.aspire.aspireias"
    },
    "cordova-plugin-globalization": {
      "PACKAGE_NAME": "com.aspire.aspireias"
    },
    "cordova-plugin-inappbrowser": {
      "PACKAGE_NAME": "com.aspire.aspireias"
    },
    "cordova-plugin-media-capture": {
      "PACKAGE_NAME": "com.aspire.aspireias"
    },
    "cordova-plugin-network-information": {
      "PACKAGE_NAME": "com.aspire.aspireias"
    },
    "cordova-plugin-splashscreen": {
      "PACKAGE_NAME": "com.aspire.aspireias"
    },
    "cordova-plugin-statusbar": {
      "PACKAGE_NAME": "com.aspire.aspireias"
    },
    "cordova-plugin-whitelist": {
      "PACKAGE_NAME": "com.aspire.aspireias"
    }
  },
  "dependent_plugins": {}
}